Metadata-Version: 2.1
Name: mitopipeline
Version: 1.1.post6
Summary: Mitochondrial Genome Pipeline
Home-page: https://github.com/timmykuo/mitopipeline
Author: Timothy Kuo
Author-email: timykuo@gmail.com
License: MIT
Download-URL: https://github.com/timmykuo/mitopipeline/releases/tag/v1.0
Keywords: genetics research data pipeline dependency management mitochondrial genome
Platform: UNKNOWN
Classifier: Development Status :: 5 - Production/Stable
Classifier: Environment :: Console
Classifier: License :: OSI Approved :: MIT License
Classifier: Programming Language :: Python :: 3
Classifier: Topic :: Sociology :: Genealogy
